Workbook

Sheet LEIA_ME
A1: Energy Trading Copilot — modelo da Entrega 2
A3: Amarelo = INPUT (editavel). Azul = FORMULA (nao sobrescrever).
A4: Todas as celulas de calculo sao formulas vivas. Nenhum valor foi colado.
A6: Aba | B6: Conteudo
A7: INPUTS | B7: Premissas, volume, precos, taxa de desconto e data-base
A8: FONTES_CURVA | B8: Origem de cada preco, classificacao e evidence_id
A9: POSICAO | B9: Dimensionamento: MWmed, horas, MWh, notional
A10: CENARIOS_PNL | B10: P&L por cenario hidrologico
A11: VAR | B11: VaR, add-ons, VaR total e consumo do limite
A12: MARGEM_NPV | B12: Resultado descontado ate 31/12
A13: CHECKS | B13: Validacoes de consistencia
A15: ATENCAO: preencher com dados reais da data-base antes de entregar.

Sheet INPUTS
A1: Parametro | B1: Valor | C1: Unidade | D1: Fonte | E1: Data-base | F1: Classificacao
A2: Volume | B2: 50 | C2: MWmed | D2: Decisao da mesa | E2: 2026-08-14 | F2: manual
A3: Preco de entrada | B3: 195 | C3: R$/MWh | D3: PREENCHER | E3: 2026-08-14 | F3: PREENCHER
A4: Preco de mercado | B4: 205 | C4: R$/MWh | D4: PREENCHER | E4: 2026-08-14 | F4: PREENCHER
A5: Lado (1=comprado, -1=vendido) | B5: -1 | C5: sinal | D5: Decisao da mesa | E5: 2026-08-14 | F5: manual
A6: Inicio da entrega | B6: 2027-01-01 | C6: data | D6: Decisao da mesa | E6: 2026-08-14 | F6: manual
A7: Fim da entrega | B7: 2027-12-31 | C7: data | D7: Decisao da mesa | E7: 2026-08-14 | F7: manual
A8: Volatilidade diaria | B8: 0.018 | C8: fracao | D8: Motor quant | E8: 2026-08-14 | F8: projetado
A9: Confianca do VaR | B9: 0.95 | C9: fracao | D9: Premissa PR-03 | E9: 2026-08-14 | F9: manual
A10: Horizonte do VaR | B10: 21 | C10: dias uteis | D10: Premissa PR-03 | E10: 2026-08-14 | F10: manual
A11: Limite de VaR | B11: 50000000 | C11: R$ | D11: Case | E11: 2026-08-14 | F11: manual
A12: Taxa de desconto | B12: 0.1 | C12: a.a. | D12: Premissa da mesa | E12: 2026-08-14 | F12: manual
A13: Add-on de proxy | B13: 0 | C13: fracao | D13: quant/addons.py | E13: 2026-08-14 | F13: manual
A14: Add-on de risco de modelo | B14: 0.1 | C14: fracao | D14: quant/addons.py | E14: 2026-08-14 | F14: manual

Sheet FONTES_CURVA
A1: Tenor | B1: Inicio | C1: Fim | D1: Preco | E1: Unidade | F1: Tipo de cotacao | G1: Origem | H1: Fonte | I1: Data-base | J1: evidence_id
A2: A+1 | B2: PREENCHER | C2: PREENCHER | D2: PREENCHER | E2: PREENCHER | F2: PREENCHER | G2: PREENCHER | H2: PREENCHER | I2: PREENCHER | J2: PREENCHER
A3: A+2 | B3: PREENCHER | C3: PREENCHER | D3: PREENCHER | E3: PREENCHER | F3: PREENCHER | G3: PREENCHER | H3: PREENCHER | I3: PREENCHER | J3: PREENCHER
A4: A+3 | B4: PREENCHER | C4: PREENCHER | D4: PREENCHER | E4: PREENCHER | F4: PREENCHER | G4: PREENCHER | H4: PREENCHER | I4: PREENCHER | J4: PREENCHER
A6: PLD e CMO NAO sao curva forward negociada. Se usados como referencia, marque Origem=PROXY_SPOT e aplique o add-on.

Sheet POSICAO
A1: Item | B1: Formula / valor | C1: Unidade
A2: Volume | B2: =INPUTS!B2 | C2: MWmed
A3: Dias do periodo | B3: =INPUTS!B6-INPUTS!B5+1 | C3: dias
A4: Horas do periodo | B4: =B3*24 | C4: h
A5: Volume em energia | B5: =B2*B4 | C5: MWh
A6: Preco de entrada | B6: =INPUTS!B3 | C6: R$/MWh
A7: Notional | B7: =B5*B6 | C7: R$
A8: Lado | B8: =INPUTS!B5 | C8: sinal
A9: Exposicao assinada | B9: =B8*B5*INPUTS!B4 | C9: R$

Sheet CENARIOS_PNL
A1: Cenario | B1: Multiplicador | C1: Preco do cenario | D1: P&L | E1: Probabilidade | F1: P&L ponderado | G1: O que muda na tese
A2: BASE | B2: 1 | C2: =INPUTS!$B$4*B2 | D2: =POSICAO!$B$5*(INPUTS!$B$3-C2)*INPUTS!$B$5*-1 | E2: 0.5 | F2: =D2*E2 | G2: Tese mantida; reavaliar na data prevista.
A3: SECO | B3: 1.35 | C3: =INPUTS!$B$4*B3 | D3: =POSICAO!$B$5*(INPUTS!$B$3-C3)*INPUTS!$B$5*-1 | E3: 0.3 | F3: =D3*E3 | G3: Vendido perde; checar gatilho de saida.
A4: UMIDO | B4: 0.75 | C4: =INPUTS!$B$4*B4 | D4: =POSICAO!$B$5*(INPUTS!$B$3-C4)*INPUTS!$B$5*-1 | E4: 0.2 | F4: =D4*E4 | G4: Vendido ganha; avaliar realizacao parcial.
A5: EXTREMO | B5: 1.8 | C5: =INPUTS!$B$4*B5 | D5: =POSICAO!$B$5*(INPUTS!$B$3-C5)*INPUTS!$B$5*-1 | E5: 0 | F5: =D5*E5 | G5: Estresse, nao previsao: dimensiona cauda.
A6: Esperanca (sem estresse) | F6: =SUM(F2:F4)

Sheet VAR
A1: Item | B1: Formula | C1: Unidade
A2: Exposicao | B2: =ABS(POSICAO!B9) | C2: R$
A3: Volatilidade diaria | B3: =INPUTS!B8 | C3: fracao
A4: z (confianca) | B4: =NORM.S.INV(INPUTS!B9) | C4: -
A5: Raiz do horizonte | B5: =SQRT(INPUTS!B10) | C5: -
A6: VaR de mercado | B6: =B2*B3*B4*B5 | C6: R$
A7: Add-on de proxy | B7: =B2*INPUTS!B13 | C7: R$
A8: Add-on de risco de modelo | B8: =B6*INPUTS!B14 | C8: R$
A9: VaR total | B9: =B6+B7+B8 | C9: R$
A10: Limite | B10: =INPUTS!B11 | C10: R$
A11: Consumo do limite | B11: =B9/B10 | C11: fracao
A12: Dentro do limite? | B12: =IF(B9<=B10,"SIM","NAO — BLOQUEADA") | C12: -

Sheet MARGEM_NPV
A1: Item | B1: Formula | C1: Unidade
A2: P&L esperado | B2: =CENARIOS_PNL!F6 | C2: R$
A3: Data-base | B3: =INPUTS!B6 | C3: data
A4: Dias ate 31/12 | B4: =DATE(YEAR(INPUTS!B6),12,31)-INPUTS!B6 | C4: dias
A5: Taxa anual | B5: =INPUTS!B12 | C5: a.a.
A6: Fator de desconto | B6: =1+B5*B4/365 | C6: -
A7: NPV ate 31/12 | B7: =B2/B6 | C7: R$

Sheet CHECKS
A1: Verificacao | B1: Resultado | C1: Esperado
A2: Horas do periodo = 8760 ou 8784 | B2: =IF(OR(POSICAO!B4=8760,POSICAO!B4=8784),"OK","ERRO") | C2: OK
A3: MWh > 0 | B3: =IF(POSICAO!B5>0,"OK","ERRO") | C3: OK
A4: VaR total <= limite | B4: =IF(VAR!B9<=VAR!B10,"OK","ESTOUROU") | C4: OK
A5: Probabilidades somam 1 | B5: =IF(ABS(SUM(CENARIOS_PNL!E2:E4)-1)<0.001,"OK","ERRO") | C5: OK
A6: Ha 2+ cenarios hidrologicos | B6: =IF(COUNTA(CENARIOS_PNL!A2:A5)>=2,"OK","ERRO") | C6: OK
A7: Fontes da curva preenchidas | B7: =IF(COUNTIF(FONTES_CURVA!H2:H4,"PREENCHER")=0,"OK","PENDENTE") | C7: OK
